.gitignore
.travis.yml
CHANGES.txt
CONTRIBUTORS.txt
LICENSE
MANIFEST.in
README.md
bootstrap.py
buildout.cfg
setup.py
travis.cfg
docs/LICENSE.GPL
docs/LICENSE.txt
src/customer/__init__.py
src/customer.lascatalinascr_com.egg-info/PKG-INFO
src/customer.lascatalinascr_com.egg-info/SOURCES.txt
src/customer.lascatalinascr_com.egg-info/dependency_links.txt
src/customer.lascatalinascr_com.egg-info/entry_points.txt
src/customer.lascatalinascr_com.egg-info/namespace_packages.txt
src/customer.lascatalinascr_com.egg-info/not-zip-safe
src/customer.lascatalinascr_com.egg-info/requires.txt
src/customer.lascatalinascr_com.egg-info/top_level.txt
src/customer/lascatalinascr_com/__init__.py
src/customer/lascatalinascr_com/config.py
src/customer/lascatalinascr_com/configure.zcml
src/customer/lascatalinascr_com/migration.py
src/customer/lascatalinascr_com/testing.py
src/customer/lascatalinascr_com/vocabularies.py
src/customer/lascatalinascr_com/browser/__init__.py
src/customer/lascatalinascr_com/browser/configure.zcml
src/customer/lascatalinascr_com/browser/interfaces.py
src/customer/lascatalinascr_com/browser/templates/listing_details.pt
src/customer/lascatalinascr_com/browser/templates/listing_results.pt
src/customer/lascatalinascr_com/browser/templates/listing_summary.pt
src/customer/lascatalinascr_com/portlets/__init__.py
src/customer/lascatalinascr_com/portlets/ajax_search.py
src/customer/lascatalinascr_com/portlets/configure.zcml
src/customer/lascatalinascr_com/portlets/embedding.py
src/customer/lascatalinascr_com/portlets/filter_search.py
src/customer/lascatalinascr_com/portlets/photowall.py
src/customer/lascatalinascr_com/portlets/related_properties.py
src/customer/lascatalinascr_com/portlets/templates/ajax_template.pt
src/customer/lascatalinascr_com/portlets/templates/embedding.pt
src/customer/lascatalinascr_com/portlets/templates/filterportlet.pt
src/customer/lascatalinascr_com/portlets/templates/photowall.pt
src/customer/lascatalinascr_com/portlets/templates/relatedproperties.pt
src/customer/lascatalinascr_com/portlets/templates/searchform.pt
src/customer/lascatalinascr_com/profiles/default/browserlayer.xml
src/customer/lascatalinascr_com/profiles/default/cssregistry.xml
src/customer/lascatalinascr_com/profiles/default/jsregistry.xml
src/customer/lascatalinascr_com/profiles/default/metadata.xml
src/customer/lascatalinascr_com/profiles/default/portlets.xml
src/customer/lascatalinascr_com/static_content/ajaxSearch.js
