Metadata-Version: 1.0
Name: customer.lascatalinascr-com
Version: 1.6
Summary: Custom Implementations of the propertyshelf MLS embedding for lascatalinascr.com
Home-page: https://github.com/propertyshelf/customer.lascatalinascr_com
Author: Propertyshelf, Inc.
Author-email: development@propertyshelf.com
License: gpl
Keywords: Plone LasCatalinas Propertyshelf
Platform: UNKNOWN
Classifier: Environment :: Web Environment
Classifier: Operating System :: OS Independent
Classifier: Framework :: Zope2
Classifier: Framework :: Plone
Classifier: Framework :: Plone :: 4.2
Classifier: Framework :: Plone :: 4.3
Classifier: Programming Language :: Python
Classifier: Programming Language :: Python :: 2.6
Classifier: Programming Language :: Python :: 2.7
Classifier: Topic :: Software Development :: Libraries :: Python Modules
